{
	"name": "Discodeit Local v2",
	"values": [
		{
			"key": "baseUrl",
			"value": "http://localhost:8080",
			"enabled": true
		},
		{
			"key": "userId1",
			"value": "",
			"enabled": true
		},
		{
			"key": "userId2",
			"value": "",
			"enabled": true
		},
		{
			"key": "userId3",
			"value": "",
			"enabled": true
		},
		{
			"key": "channelId1",
			"value": "",
			"enabled": true
		},
		{
			"key": "channelId2",
			"value": "",
			"enabled": true
		},
		{
			"key": "channelId3",
			"value": "",
			"enabled": true
		},
		{
			"key": "privateChannelId",
			"value": "",
			"enabled": true
		},
		{
			"key": "messageId1",
			"value": "",
			"enabled": true
		},
		{
			"key": "messageId2",
			"value": "",
			"enabled": true
		},
		{
			"key": "readStatusId1",
			"value": "",
			"enabled": true
		},
		{
			"key": "binaryContentId",
			"value": "",
			"enabled": true
		}
	]
}
